{
  "pages": [
    {
      "path": "pages/index/index",
      "style": {
        "navigationBarTitleText": "刷刷",
        "navigationBarTextStyle": "white",
        "navigationBarBackgroundColor": "#000000"
      }
    },
    {
      "path": "pages/find/index",
      "style": {
        "navigationBarTitleText": "找片",
        "navigationBarTextStyle": "black",
        "navigationBarBackgroundColor": "#ffffff"
      }
    },
    {
      "path": "pages/welfare/index",
      "style": {
        "navigationBarTitleText": "福利",
        "navigationBarTextStyle": "black",
        "navigationBarBackgroundColor": "#ffffff"
      }
    },
    {
      "path": "pages/mine/index",
      "style": {
        "navigationBarTitleText": "我的",
        "navigationBarTextStyle": "black",
        "navigationBarBackgroundColor": "#ffffff"
      }
    }
  ],
  "globalStyle": {
    "navigationBarTextStyle": "black",
    "navigationBarTitleText": "山狸漫剧",
    "navigationBarBackgroundColor": "#ffffff",
    "backgroundColor": "#f5f5f5"
  },
  "tabBar": {
    "color": "#999999",
    "selectedColor": "#ff4d4f",
    "backgroundColor": "#ffffff",
    "borderStyle": "black",
    "height": "50px",
    "list": [
      {
        "pagePath": "pages/index/index",
        "text": "刷刷"
      },
      {
        "pagePath": "pages/find/index",
        "text": "找片"
      },
      {
        "pagePath": "pages/welfare/index",
        "text": "福利"
      },
      {
        "pagePath": "pages/mine/index",
        "text": "我的"
      }
    ]
  }
}